ag2_persona/__init__.py
ag2_persona/async_persona_builder.py
ag2_persona/parsers.py
ag2_persona/persona_agent.py
ag2_persona/persona_builder.py
ag2_persona/py.typed
ag2_persona-0.1.3.dist-info/METADATA
ag2_persona-0.1.3.dist-info/WHEEL
ag2_persona-0.1.3.dist-info/licenses/LICENSE
ag2_persona-0.1.3.dist-info/RECORD
