Metadata-Version: 2.4
Name: ag2-persona
Version: 0.1.3
Summary: Persona-based agents for AG2 (AutoGen) - enabling distinct character embodiment
Project-URL: Homepage, https://github.com/rsnodgrass/ag2-persona
Project-URL: Documentation, https://rsnodgrass.github.io/ag2-persona/
Project-URL: Repository, https://github.com/rsnodgrass/ag2-persona.git
Project-URL: Issues, https://github.com/rsnodgrass/ag2-persona/issues
Author-email: Ryan Snodgrass <rsnodgrass@gmail.com>
Maintainer-email: Ryan Snodgrass <rsnodgrass@gmail.com>
License-File: LICENSE
Keywords: ag2,agents,autogen,character,llm,persona,roleplay
Classifier: Development Status :: 4 - Beta
Classifier: Intended Audience :: Developers
Classifier: Operating System :: OS Independent
Classifier: Programming Language :: Python :: 3
Classifier: Programming Language :: Python :: 3.11
Classifier: Programming Language :: Python :: 3.12
Classifier: Programming Language :: Python :: 3.13
Classifier: Programming Language :: Python :: 3.14
Classifier: Topic :: Scientific/Engineering :: Artificial Intelligence
Classifier: Topic :: Software Development :: Libraries :: Python Modules
Requires-Python: >=3.11
Requires-Dist: aiofiles>=24.1.0
Requires-Dist: pyautogen>=0.2.0
Requires-Dist: python-frontmatter>=1.1.0
Requires-Dist: ruamel-yaml>=0.18
Provides-Extra: dev
Requires-Dist: mkdocs-material>=9.4.0; extra == 'dev'
Requires-Dist: mkdocs>=1.5.3; extra == 'dev'
Requires-Dist: mkdocstrings[python]>=0.24.0; extra == 'dev'
Requires-Dist: mypy>=1.12; extra == 'dev'
Requires-Dist: pre-commit>=4.0.1; extra == 'dev'
Requires-Dist: pytest-asyncio>=0.24.0; extra == 'dev'
Requires-Dist: pytest-cov>=5.0; extra == 'dev'
Requires-Dist: pytest>=8.3; extra == 'dev'
Requires-Dist: ruff>=0.6.9; extra == 'dev'
Requires-Dist: types-aiofiles>=24.1.0; extra == 'dev'
